pycommons/__init__.py
pycommons/py.typed
pycommons/types.py
pycommons/version.py
pycommons/dev/__init__.py
pycommons/dev/url_replacer.py
pycommons/dev/building/__init__.py
pycommons/dev/building/build_info.py
pycommons/dev/building/make_dist.py
pycommons/dev/building/make_documentation.py
pycommons/dev/building/run_tests.py
pycommons/dev/building/static_analysis.py
pycommons/dev/doc/__init__.py
pycommons/dev/doc/doc_info.py
pycommons/dev/doc/index_rst.py
pycommons/dev/doc/process_md.py
pycommons/dev/doc/setup_doc.py
pycommons/dev/tests/__init__.py
pycommons/dev/tests/compile_and_run.py
pycommons/dev/tests/examples_in_dir.py
pycommons/dev/tests/examples_in_md.py
pycommons/dev/tests/links_in_md.py
pycommons/ds/__init__.py
pycommons/ds/cache.py
pycommons/ds/immutable_map.py
pycommons/ds/sequences.py
pycommons/io/__init__.py
pycommons/io/arguments.py
pycommons/io/console.py
pycommons/io/csv.py
pycommons/io/parser.py
pycommons/io/path.py
pycommons/io/temp.py
pycommons/math/__init__.py
pycommons/math/int_math.py
pycommons/math/primes.py
pycommons/math/rank.py
pycommons/math/sample_statistics.py
pycommons/math/stream_statistics.py
pycommons/math/streams.py
pycommons/net/__init__.py
pycommons/net/url.py
pycommons/processes/__init__.py
pycommons/processes/caller.py
pycommons/processes/python.py
pycommons/processes/shell.py
pycommons/processes/system_state.py
pycommons/strings/__init__.py
pycommons/strings/chars.py
pycommons/strings/enforce.py
pycommons/strings/string_conv.py
pycommons/strings/string_tools.py
pycommons-0.8.81.dist-info/licenses/LICENSE
pycommons-0.8.81.dist-info/METADATA
pycommons-0.8.81.dist-info/WHEEL
pycommons-0.8.81.dist-info/top_level.txt
pycommons-0.8.81.dist-info/RECORD
