Metadata-Version: 2.4
Name: pycommons
Version: 0.8.81
Summary: A package with utility functionality for Python projects.
Home-page: https://thomasweise.github.io/pycommons
Author: Thomas Weise
Author-email: tweise@ustc.edu.cn
Maintainer: Thomas Weise
Maintainer-email: tweise@ustc.edu.cn
License: GPL 3.0
Project-URL: Documentation, https://thomasweise.github.io/pycommons
Project-URL: Source, https://github.com/thomasWeise/pycommons/
Project-URL: Tracker, https://github.com/thomasWeise/pycommons/issues
Keywords: utilities
Classifier: Development Status :: 4 - Beta
Classifier: Intended Audience :: Developers
Classifier: Natural Language :: English
Classifier: Operating System :: Microsoft :: Windows
Classifier: Operating System :: POSIX :: Linux
Classifier: Programming Language :: Python :: 3 :: Only
Classifier: Programming Language :: Python :: 3.12
Requires-Python: >=3.12
License-File: LICENSE
Requires-Dist: psutil>=7.1.3
Provides-Extra: dev
Requires-Dist: autoflake>=2.3.1; extra == "dev"
Requires-Dist: bandit>=1.9.2; extra == "dev"
Requires-Dist: certifi>=2025.11.12; extra == "dev"
Requires-Dist: coverage>=7.13.0; extra == "dev"
Requires-Dist: coverage-badge>=1.1.2; extra == "dev"
Requires-Dist: dlint>=0.16.0; extra == "dev"
Requires-Dist: dodgy>=0.2.1; extra == "dev"
Requires-Dist: flake8>=7.3.0; extra == "dev"
Requires-Dist: flake8-bugbear>=25.11.29; extra == "dev"
Requires-Dist: flake8-eradicate>=1.5.0; extra == "dev"
Requires-Dist: flake8-use-fstring>=1.4; extra == "dev"
Requires-Dist: markdown>=3.10; extra == "dev"
Requires-Dist: minify_html>=0.18.1; extra == "dev"
Requires-Dist: mypy>=1.19.0; extra == "dev"
Requires-Dist: myst-parser>=4.0.1; extra == "dev"
Requires-Dist: pycodestyle>=2.14.0; extra == "dev"
Requires-Dist: pydocstyle>=6.3.0; extra == "dev"
Requires-Dist: pyflakes>=3.4.0; extra == "dev"
Requires-Dist: pylint>=4.0.4; extra == "dev"
Requires-Dist: pyroma>=5.0.1; extra == "dev"
Requires-Dist: pytest>=9.0.2; extra == "dev"
Requires-Dist: pytest-timeout>=2.4.0; extra == "dev"
Requires-Dist: ruff>=0.14.8; extra == "dev"
Requires-Dist: setuptools>=80.9.0; extra == "dev"
Requires-Dist: sphinx>=8.2.3; extra == "dev"
Requires-Dist: sphinx-autodoc-typehints>=3.5.2; extra == "dev"
Requires-Dist: testresources>=2.0.2; extra == "dev"
Requires-Dist: tryceratops>=2.4.1; extra == "dev"
Requires-Dist: twine>=6.2.0; extra == "dev"
Requires-Dist: unimport>=1.3.0; extra == "dev"
Requires-Dist: urllib3>=2.6.1; extra == "dev"
Requires-Dist: virtualenv>=20.35.4; extra == "dev"
Requires-Dist: vulture>=2.14; extra == "dev"
Requires-Dist: wheel>=0.45.1; extra == "dev"
Dynamic: description
Dynamic: description-content-type
Dynamic: license-file
